__init__.py
thttp.py
thttp-1.3.0.dist-info/LICENSE.md
thttp-1.3.0.dist-info/METADATA
thttp-1.3.0.dist-info/WHEEL
thttp-1.3.0.dist-info/top_level.txt
thttp-1.3.0.dist-info/RECORD
