Metadata-Version: 2.1
Name: thttp
Version: 1.3.0
Summary: An incredibly lightweight wrapper around urllib
Home-page: https://github.com/sesh/thttp
Author: Brenton Cleeland
Author-email: brenton@brntn.me
Project-URL: Bug Tracker, https://github.com/sesh/thttp/issues
Classifier: Programming Language :: Python :: 3
Requires-Python: >=3.6
License-File: LICENSE.md
